LICENSE
MANIFEST.in
README.rst
setup.py
django_password_reset_fc.egg-info/PKG-INFO
django_password_reset_fc.egg-info/SOURCES.txt
django_password_reset_fc.egg-info/dependency_links.txt
django_password_reset_fc.egg-info/not-zip-safe
django_password_reset_fc.egg-info/requires.txt
django_password_reset_fc.egg-info/top_level.txt
password_reset/__init__.py
password_reset/forms.py
password_reset/mail.py
password_reset/urls.py
password_reset/views.py
password_reset/locale/ru/LC_MESSAGES/django.mo
password_reset/locale/ru/LC_MESSAGES/django.po
password_reset/templates/password_reset/base.html
password_reset/templates/password_reset/recovery_done.html
password_reset/templates/password_reset/recovery_form.html
password_reset/templates/password_reset/recovery_letter.html
password_reset/templates/password_reset/reset.html
password_reset/templates/password_reset/reset_sent.html
password_reset/tests/__init__.py
password_reset/tests/models.py
password_reset/tests/settings.py
password_reset/tests/tests.py
password_reset/tests/urls.py
password_reset/tests/views.py