Metadata-Version: 1.0
Name: django-password-reset-fc
Version: 0.6.2
Summary: Class-based views for password reset.
Home-page: https://github.com/brutasse/django-password-reset
Author: Ilya Baryshev
Author-email: baryshev@futurecolors.ru
License: BSD licence, see LICENSE file
Platform: UNKNOWN
Classifier: Development Status :: 4 - Beta
Classifier: Environment :: Web Environment
Classifier: Framework :: Django
Classifier: Intended Audience :: Developers
Classifier: License :: OSI Approved :: BSD License
Classifier: Natural Language :: English
Classifier: Programming Language :: Python
